thenewallinone/__init__.py
thenewallinone-5.0.9.dist-info/licenses/LICENSE
thenewallinone-5.0.9.dist-info/METADATA
thenewallinone-5.0.9.dist-info/WHEEL
thenewallinone-5.0.9.dist-info/top_level.txt
thenewallinone-5.0.9.dist-info/RECORD
