Metadata-Version: 2.4
Name: thenewallinone
Version: 5.0.9
Summary: A simple test library for PyPI
Author: Agamjot Lamba
Author-email: agamjotlamba55@gmail.com
Classifier: Programming Language :: Python :: 3
Classifier: License :: OSI Approved :: MIT License
Classifier: Operating System :: OS Independent
Requires-Python: >=3.6
License-File: LICENSE
Requires-Dist: huggingface_hub
Requires-Dist: transformers
Requires-Dist: pillow
Requires-Dist: torch
Dynamic: author
Dynamic: author-email
Dynamic: classifier
Dynamic: description
Dynamic: description-content-type
Dynamic: license-file
Dynamic: requires-dist
Dynamic: requires-python
Dynamic: summary
